odoo/addons/cms_toolbar_example/README.rst
odoo/addons/cms_toolbar_example/__init__.py
odoo/addons/cms_toolbar_example/__manifest__.py
odoo/addons/cms_toolbar_example/controllers/__init__.py
odoo/addons/cms_toolbar_example/controllers/main.py
odoo/addons/cms_toolbar_example/data/examples.xml
odoo/addons/cms_toolbar_example/data/ir.model.access.csv
odoo/addons/cms_toolbar_example/models/__init__.py
odoo/addons/cms_toolbar_example/models/example.py
odoo/addons/cms_toolbar_example/static/description/icon.png
odoo/addons/cms_toolbar_example/templates/example.xml
odoo11_addon_cms_toolbar_example-11.0.1.0.0.dist-info/DESCRIPTION.rst
odoo11_addon_cms_toolbar_example-11.0.1.0.0.dist-info/METADATA
odoo11_addon_cms_toolbar_example-11.0.1.0.0.dist-info/RECORD
odoo11_addon_cms_toolbar_example-11.0.1.0.0.dist-info/WHEEL
odoo11_addon_cms_toolbar_example-11.0.1.0.0.dist-info/metadata.json
odoo11_addon_cms_toolbar_example-11.0.1.0.0.dist-info/top_level.txt
